{
  "orchestrator": {
    "status": "idle",
    "phase": null,
    "base_branch": "main"
  },
  "features": {
    "FEAT-001": {
      "title": "Export size selection — As Is / Small / Custom with locked aspect ratio",
      "status": "draft",
      "deps": [],
      "plan": "docs/backlog/features/FEAT-001_export-size-selection.md",
      "branch": null,
      "merged": false,
      "skill": "canvas"
    },
    "FEAT-002": {
      "title": "Project persistence and explorer",
      "status": "done",
      "deps": [],
      "plan": "docs/backlog/features/FEAT-002_project-persistence-explorer.md",
      "branch": null,
      "merged": false,
      "skill": null
    },
    "FEAT-003": {
      "title": "Mobile touch reliability and iOS install fallback",
      "status": "done",
      "deps": [
        "FEAT-002"
      ],
      "plan": "docs/backlog/features/FEAT-003_mobile-touch-and-ios-install.md",
      "branch": null,
      "merged": false,
      "skill": "pwa"
    }
  },
  "bugfixes": {},
  "refactors": {},
  "tests": {},
  "queue": [],
  "active": [],
  "history": [],
  "errors": []
}
